fileformats/common/__init__.py
fileformats/common/_version.py
fileformats/common/archive.py
fileformats/common/base.py
fileformats/common/document.py
fileformats/common/image.py
fileformats/common/numeric.py
fileformats/common/text.py
fileformats/common/utils.py
fileformats/common/converters/__init__.py
fileformats/common/converters/archive.py
fileformats/common/converters/tests/test_archive.py
fileformats_common-0.1.3.dist-info/LICENSE
fileformats_common-0.1.3.dist-info/WHEEL
fileformats_common-0.1.3.dist-info/METADATA
fileformats_common-0.1.3.dist-info/RECORD
