Metadata-Version: 2.1
Name: fileformats-common
Version: 0.1.3
Summary: Python classes for specifying fileformats for type-hinting and automatic-conversion
Keywords: file formats,data
Author-email: "Thomas G. Close" <tom.g.close@gmail.com>
Maintainer-email: "Thomas G. Close" <tom.g.close@gmail.com>
Requires-Python: >=3.8
Classifier: Development Status :: 3 - Alpha
Classifier: Environment :: Console
Classifier: Intended Audience :: Science/Research
Classifier: License :: OSI Approved :: Apache Software License
Classifier: Operating System :: MacOS :: MacOS X
Classifier: Operating System :: Microsoft :: Windows
Classifier: Operating System :: POSIX :: Linux
Classifier: Programming Language :: Python :: 3.8
Classifier: Programming Language :: Python :: 3.9
Classifier: Programming Language :: Python :: 3.10
Classifier: Programming Language :: Python :: 3.11
Classifier: Topic :: Scientific/Engineering
Requires-Dist: attrs>=22.1.0
Requires-Dist: fileformats-core >=0.1
Requires-Dist: pydra >= 0.20.0
Requires-Dist: black ; extra == "dev"
Requires-Dist: pre-commit ; extra == "dev"
Requires-Dist: codespell ; extra == "dev"
Requires-Dist: flake8 ; extra == "dev"
Requires-Dist: flake8-pyproject ; extra == "dev"
Requires-Dist: pytest >=6.2.5 ; extra == "test"
Requires-Dist: pytest-env>=0.6.2 ; extra == "test"
Requires-Dist: pytest-cov>=2.12.1 ; extra == "test"
Requires-Dist: codecov ; extra == "test"
Project-URL: repository, https://github.com/ArcanaFramework/fileformats-common
Provides-Extra: dev
Provides-Extra: test
